cbayes/__init__.py
cbayes/distributions.py
cbayes/sample.py
cbayes/solve.py
cbayes-0.4.post3.dist-info/LICENSE
cbayes-0.4.post3.dist-info/METADATA
cbayes-0.4.post3.dist-info/WHEEL
cbayes-0.4.post3.dist-info/top_level.txt
cbayes-0.4.post3.dist-info/RECORD
