Metadata-Version: 2.1
Name: cbayes
Version: 0.4.post3
Summary: Consistent Bayesian Inversion
Home-page: https://github.com/mpilosov/ConsistentBayes/
Author: Michael Pilosov
Author-email: mpilosov@gmail.com
License: MIT
Platform: UNKNOWN
License-File: LICENSE
Requires-Dist: scipy
Requires-Dist: numpy
Requires-Dist: scikit-learn
